tfc.v
`timescale 1ns/1ps

module traffic_light_controller (
    input  clk,
    input  rst,
    input  X,
    output reg [1:0] hwy,
    output reg [1:0] cntry
);

    // light codes
    parameter R = 0, Y = 1, G = 2;
    // states
    parameter S0 = 0, S1 = 1, S2 = 2, S3 = 3, S4 = 4;
    // how many clock cycles to hold each yellow/all-red phase
    parameter Y2R = 2, R2G = 2;

    reg [2:0] state, next_state;
    reg [3:0] delay_cnt;

    // state register
    always @(posedge clk or posedge rst) begin
        if (rst) state <= S0;
        else     state <= next_state;
    end

    // delay counter: resets whenever we're about to move to a new state
    always @(posedge clk or posedge rst) begin
        if (rst)
            delay_cnt <= 0;
        else if (state != next_state)
            delay_cnt <= 0;
        else
            delay_cnt <= delay_cnt + 1;
    end

    // output decode (Moore outputs)
    always @(*) begin
        case (state)
            S0: begin hwy = G; cntry = R; end
            S1: begin hwy = Y; cntry = R; end
            S2: begin hwy = R; cntry = R; end
            S3: begin hwy = R; cntry = G; end
            S4: begin hwy = R; cntry = Y; end
            default: begin hwy = R; cntry = R; end
        endcase
    end

    // next-state logic (combinational)
    always @(*) begin
        if (rst) begin
            next_state = S0;
        end else begin
            case (state)
                S0: next_state = X ? S1 : S0;
                S1: next_state = (delay_cnt >= Y2R-1) ? S2 : S1;
                S2: next_state = (delay_cnt >= R2G-1) ? S3 : S2;
                S3: next_state = X ? S3 : S4;
                S4: next_state = (delay_cnt >= Y2R-1) ? S0 : S4;
                default: next_state = S0;
            endcase
        end
    end

endmodule


// Testbench
module tb;

    reg clk = 0, rst, X;
    wire [1:0] hwy, cntry;

    traffic_light_controller dut (
        .clk(clk), .rst(rst), .X(X),
        .hwy(hwy), .cntry(cntry)
    );

    // 10ns period clock
    always #5 clk = ~clk;

    // small helper so waveform/monitor prints are readable
    function [7:0] name;
        input [1:0] code;
        begin
            case (code)
                0: name = "R";
                1: name = "Y";
                2: name = "G";
                default: name = "?";
            endcase
        end
    endfunction

    initial begin
        $dumpfile("traffic.vcd");
        $dumpvars(0, tb);

        rst = 1; X = 0;
        #12 rst = 0;      // release reset after a couple clocks
        #20 X = 1;        // car arrives on country road
        #10 X = 0;
        #100 X = 1;       // car stays present for a while
        #40 X = 0;
        #200 $finish;
    end

    // $monitor only accepts simple signals/constants, not function calls,
    // so we use an always block + $display (called procedurally) instead.
    always @(dut.state or hwy or cntry or X) begin
        $display("t=%0t state=%0d hwy=%s cntry=%s X=%b",
                  $time, dut.state, name(hwy), name(cntry), X);
    end

endmodule

traffic.vcd
$date
	Mon Jul 06 22:38:55 2026
$end
$version
	Icarus Verilog
$end
$timescale
	1ps
$end
$scope module tb $end
$var wire 2 ! hwy [1:0] $end
$var wire 2 " cntry [1:0] $end
$var reg 1 # X $end
$var reg 1 $ clk $end
$var reg 1 % rst $end
$scope function name $end
$var reg 2 & code [1:0] $end
$upscope $end
$scope module dut $end
$var wire 1 # X $end
$var wire 1 $ clk $end
$var wire 1 % rst $end
$var reg 2 ' cntry [1:0] $end
$var reg 4 ( delay_cnt [3:0] $end
$var reg 2 ) hwy [1:0] $end
$var reg 3 * next_state [2:0] $end
$var reg 3 + state [2:0] $end
$upscope $end
$upscope $end
$enddefinitions $end
#0
$dumpvars
b0 +
b0 *
b10 )
b0 (
b0 '
b0 &
1%
0$
0#
b0 "
b10 !
$end
#5000
1$
#10000
0$
#12000
0%
#15000
b1 (
1$
#20000
0$
#25000
b10 (
1$
#30000
0$
#32000
b1 *
b0 &
1#
#35000
b1 !
b1 )
b0 &
b1 +
b0 (
1$
#40000
0$
#42000
b0 &
0#
#45000
b10 *
b1 (
1$
#50000
0$
#55000
b0 !
b0 )
b0 &
b10 +
b0 (
1$
#60000
0$
#65000
b11 *
b1 (
1$
#70000
0$
#75000
b10 &
b10 "
b10 '
b100 *
b11 +
b0 (
1$
#80000
0$
#85000
b1 "
b1 '
b1 &
b100 +
1$
#90000
0$
#95000
b0 *
b1 (
1$
#100000
0$
#105000
b0 "
b0 '
b10 !
b10 )
b0 &
b0 (
b0 +
1$
#110000
0$
#115000
b1 (
1$
#120000
0$
#125000
b10 (
1$
#130000
0$
#135000
b11 (
1$
#140000
0$
#142000
b1 *
b0 &
1#
#145000
b1 !
b1 )
b0 &
b0 (
b1 +
1$
#150000
0$
#155000
b10 *
b1 (
1$
#160000
0$
#165000
b0 !
b0 )
b0 &
b0 (
b10 +
1$
#170000
0$
#175000
b11 *
b1 (
1$
#180000
0$
#182000
0#
#185000
b10 &
b100 *
b10 "
b10 '
b0 (
b11 +
1$
#190000
0$
#195000
b1 "
b1 '
b1 &
b100 +
1$
#200000
0$
#205000
b0 *
b1 (
1$
#210000
0$
#215000
b0 "
b0 '
b10 !
b10 )
b0 &
b0 +
b0 (
1$
#220000
0$
#225000
b1 (
1$
#230000
0$
#235000
b10 (
1$
#240000
0$
#245000
b11 (
1$
#250000
0$
#255000
b100 (
1$
#260000
0$
#265000
b101 (
1$
#270000
0$
#275000
b110 (
1$
#280000
0$
#285000
b111 (
1$
#290000
0$
#295000
b1000 (
1$
#300000
0$
#305000
b1001 (
1$
#310000
0$
#315000
b1010 (
1$
#320000
0$
#325000
b1011 (
1$
#330000
0$
#335000
b1100 (
1$
#340000
0$
#345000
b1101 (
1$
#350000
0$
#355000
b1110 (
1$
#360000
0$
#365000
b1111 (
1$
#370000
0$
#375000
b0 (
1$
